[
  {
    "id": "春",
    "word": "春",
    "reading": "はる",
    "pos": "noun",
    "meaning": "spring (season)",
    "notes": "One of four seasons. Spring in Japan runs from March to May.",
    "jlpt": "N5",
    "frequency": 6,
    "examples": [
      {
        "japanese": "春だ！春が来たんだ！",
        "english": "It's spring! Spring has come!",
        "note": "だ (copula) + んだ (emphasis)",
        "furigana": "<ruby>春<rt>はる</rt></ruby>だ！<ruby>春<rt>はる</rt></ruby>が<ruby>来<rt>き</rt></ruby>たんだ！"
      },
      {
        "japanese": "暖かい春からこの物語を始めることにしましょう",
        "english": "Let's start this story in warm spring.",
        "note": "adjective + noun pattern",
        "furigana": "<ruby>暖<rt>あたた</rt></ruby>かい<ruby>春<rt>はる</rt></ruby>からこの<ruby>物語<rt>ものがたり</rt></ruby>を<ruby>始<rt>はじ</rt></ruby>めることにしましょう"
      }
    ]
  },
  {
    "id": "来る",
    "word": "来る",
    "reading": "くる",
    "pos": "verb (irregular)",
    "meaning": "to come",
    "notes": "Irregular verb. Past: 来た (きた). Te-form: 来て (きて). Imperative: おいで.",
    "jlpt": "N5",
    "frequency": 12,
    "examples": [
      {
        "japanese": "春が来たんだ！",
        "english": "Spring has come!",
        "note": "past tense (た-form)",
        "furigana": "<ruby>春<rt>はる</rt></ruby>が<ruby>来<rt>き</rt></ruby>たんだ！"
      },
      {
        "japanese": "今年はずいぶん早く帰ってきたね",
        "english": "You came back pretty early this year.",
        "note": "帰って + きた (motion toward speaker)",
        "furigana": "<ruby>今年<rt>ことし</rt></ruby>はずいぶん<ruby>早<rt>はや</rt></ruby>く<ruby>帰<rt>かえ</rt></ruby>ってきたね"
      },
      {
        "japanese": "さあこっちにおいで",
        "english": "Now come over here.",
        "note": "おいで = polite imperative of 来る",
        "furigana": "さあこっちにおいで"
      }
    ]
  },
  {
    "id": "眠る",
    "word": "眠る",
    "reading": "ねむる",
    "pos": "verb (godan)",
    "meaning": "to sleep",
    "notes": "Intransitive verb. For 'to put to sleep,' use 寝かせる.",
    "jlpt": "N4",
    "frequency": 4,
    "examples": [
      {
        "japanese": "ほらみんな眠っていますよ",
        "english": "Look, everyone is sleeping.",
        "note": "〜ている (progressive/state)",
        "furigana": "ほらみんな<ruby>眠<rt>ねむ</rt></ruby>っていますよ"
      },
      {
        "japanese": "この谷の住民たちは冬の間眠って過ごします",
        "english": "The residents of this valley sleep through the winter.",
        "note": "〜て過ごす (spend time doing)",
        "furigana": "この<ruby>谷<rt>たに</rt></ruby>の<ruby>住民<rt>じゅうみん</rt></ruby>たちは<ruby>冬<rt>ふゆ</rt></ruby>の<ruby>間<rt>ま</rt></ruby><ruby>眠<rt>ねむ</rt></ruby>って<ruby>過<rt>す</rt></ruby>ごします"
      }
    ]
  },
  {
    "id": "起きる",
    "word": "起きる",
    "reading": "おきる",
    "pos": "verb (ichidan)",
    "meaning": "to wake up, to get up",
    "notes": "Intransitive. Compare: 起こす (to wake someone up).",
    "jlpt": "N5",
    "frequency": 3,
    "examples": [
      {
        "japanese": "起きたのね二人とも",
        "english": "You both woke up, didn't you?",
        "note": "past + explanatory のね",
        "furigana": "<ruby>起<rt>お</rt></ruby>きたのね<ruby>二<rt>に</rt></ruby><ruby>人<rt>にん</rt></ruby>とも"
      },
      {
        "japanese": "やあミー君も起きてたのか",
        "english": "Oh, Little My, you're awake too.",
        "note": "〜ていた (past progressive state)",
        "furigana": "やあミー<ruby>君<rt>きみ</rt></ruby>も<ruby>起<rt>お</rt></ruby>きてたのか"
      }
    ]
  },
  {
    "id": "帽子",
    "word": "帽子",
    "reading": "ぼうし",
    "pos": "noun",
    "meaning": "hat, cap",
    "notes": "A key item in Episode 1 - the mysterious magic hat.",
    "jlpt": "N4",
    "frequency": 10,
    "examples": [
      {
        "japanese": "あれはシルクハットだ",
        "english": "That's a top hat!",
        "note": "シルクハット = silk hat / top hat",
        "furigana": "あれはシルクハットだ"
      },
      {
        "japanese": "この帽子パパのに似てるな",
        "english": "This hat looks a lot like Dad's.",
        "note": "〜に似ている (to resemble)",
        "furigana": "この<ruby>帽子<rt>ぼうし</rt></ruby>パパのに<ruby>似<rt>に</rt></ruby>てるな"
      },
      {
        "japanese": "残念だけどこの帽子は大きすぎる",
        "english": "Unfortunately, this hat is too big.",
        "note": "〜すぎる (too much)",
        "furigana": "<ruby>残念<rt>ざんねん</rt></ruby>だけどこの<ruby>帽子<rt>ぼうし</rt></ruby>は<ruby>大<rt>おお</rt></ruby>きすぎる"
      }
    ]
  },
  {
    "id": "冬",
    "word": "冬",
    "reading": "ふゆ",
    "pos": "noun",
    "meaning": "winter",
    "notes": "One of four seasons. Moomin characters hibernate during winter.",
    "jlpt": "N5",
    "frequency": 4,
    "examples": [
      {
        "japanese": "ムーミン谷は冬になるとすっかり雪で覆われてしまうんです",
        "english": "Moominvalley gets completely covered in snow during winter.",
        "note": "〜になると (when it becomes)",
        "furigana": "ムーミン<ruby>谷<rt>たに</rt></ruby>は<ruby>冬<rt>ふゆ</rt></ruby>になるとすっかり<ruby>雪<rt>ゆき</rt></ruby>で<ruby>覆<rt>おお</rt></ruby>われてしまうんです"
      },
      {
        "japanese": "みんなが雪の下で眠っている冬から始めるわけにはいかないので",
        "english": "We can't start from winter when everyone is sleeping under the snow.",
        "note": "〜わけにはいかない (cannot do)",
        "furigana": "みんなが<ruby>雪の下<rt>ゆきのした</rt></ruby>で<ruby>眠<rt>ねむ</rt></ruby>っている<ruby>冬<rt>ふゆ</rt></ruby>から<ruby>始<rt>はじ</rt></ruby>めるわけにはいかないので"
      }
    ]
  },
  {
    "id": "冬眠",
    "word": "冬眠",
    "reading": "とうみん",
    "pos": "noun/suru verb",
    "meaning": "hibernation",
    "notes": "冬 (winter) + 眠 (sleep). The Moomin family hibernates every winter.",
    "jlpt": "N2",
    "frequency": 3,
    "examples": [
      {
        "japanese": "私どうしてこの家で冬眠してたの",
        "english": "Why was I hibernating in this house?",
        "note": "〜していた (past progressive)",
        "furigana": "<ruby>私<rt>わたし</rt></ruby>どうしてこの<ruby>家<rt>いえ</rt></ruby>で<ruby>冬眠<rt>とうみん</rt></ruby>してたの"
      },
      {
        "japanese": "冬眠明けのお料理を作ることにしましょうか",
        "english": "Shall we make some post-hibernation dishes?",
        "note": "〜明け (after/post-)",
        "furigana": "<ruby>冬眠<rt>とうみん</rt></ruby><ruby>明<rt>あ</rt></ruby>けのお<ruby>料理<rt>りょうり</rt></ruby>を<ruby>作<rt>つく</rt></ruby>ることにしましょうか"
      }
    ]
  },
  {
    "id": "谷",
    "word": "谷",
    "reading": "たに",
    "pos": "noun",
    "meaning": "valley",
    "notes": "ムーミン谷 (Moomin Valley) is the setting of the story.",
    "jlpt": "N3",
    "frequency": 3,
    "examples": [
      {
        "japanese": "みなさんはムーミン谷のことを聞いたことがありますか",
        "english": "Have you all heard of Moomin Valley?",
        "note": "〜のこと (about ~)",
        "furigana": "みなさんはムーミン<ruby>谷<rt>たに</rt></ruby>のことを<ruby>聞<rt>き</rt></ruby>いたことがありますか"
      },
      {
        "japanese": "この谷の住民たちは冬の間眠って過ごします",
        "english": "The residents of this valley sleep through the winter.",
        "note": "住民 = residents",
        "furigana": "この<ruby>谷<rt>たに</rt></ruby>の<ruby>住民<rt>じゅうみん</rt></ruby>たちは<ruby>冬<rt>ふゆ</rt></ruby>の<ruby>間<rt>ま</rt></ruby><ruby>眠<rt>ねむ</rt></ruby>って<ruby>過<rt>す</rt></ruby>ごします"
      }
    ]
  },
  {
    "id": "雪",
    "word": "雪",
    "reading": "ゆき",
    "pos": "noun",
    "meaning": "snow",
    "notes": "Common in winter scenes. 雪が降る = it snows.",
    "jlpt": "N5",
    "frequency": 2,
    "examples": [
      {
        "japanese": "ムーミン谷は冬になるとすっかり雪で覆われてしまうんです",
        "english": "Moominvalley gets completely covered in snow during winter.",
        "note": "雪で覆われる (be covered with snow)",
        "furigana": "ムーミン<ruby>谷<rt>たに</rt></ruby>は<ruby>冬<rt>ふゆ</rt></ruby>になるとすっかり<ruby>雪<rt>ゆき</rt></ruby>で<ruby>覆<rt>おお</rt></ruby>われてしまうんです"
      }
    ]
  },
  {
    "id": "家",
    "word": "家",
    "reading": "いえ",
    "pos": "noun",
    "meaning": "house, home",
    "notes": "Also read as うち when meaning 'my house/home'.",
    "jlpt": "N5",
    "frequency": 6,
    "examples": [
      {
        "japanese": "これはムーミンの家です",
        "english": "This is Moomin's house.",
        "note": "possessive の",
        "furigana": "これはムーミンの<ruby>家<rt>いえ</rt></ruby>です"
      },
      {
        "japanese": "私家でお姉ちゃんと一緒に寝てたはずだけど",
        "english": "I should have been sleeping with my big sister at home.",
        "note": "はず (should be/expectation)",
        "furigana": "<ruby>私家<rt>しか</rt></ruby>でお<ruby>姉<rt>ねえ</rt></ruby>ちゃんと<ruby>一緒<rt>いっしょ</rt></ruby>に<ruby>寝<rt>ね</rt></ruby>てたはずだけど"
      },
      {
        "japanese": "僕が家を出た時ママは起きてました",
        "english": "When I left the house, Mama was awake.",
        "note": "家を出る (leave the house)",
        "furigana": "<ruby>僕<rt>ぼく</rt></ruby>が<ruby>家<rt>いえ</rt></ruby>を<ruby>出<rt>で</rt></ruby>た<ruby>時<rt>とき</rt></ruby>ママは<ruby>起<rt>お</rt></ruby>きてました"
      }
    ]
  },
  {
    "id": "物語",
    "word": "物語",
    "reading": "ものがたり",
    "pos": "noun",
    "meaning": "story, tale",
    "notes": "物 (thing) + 語 (speak/tell). A narrative or story.",
    "jlpt": "N3",
    "frequency": 3,
    "examples": [
      {
        "japanese": "これがこの物語の主人公ムーミントロール",
        "english": "This is Moomintroll, the main character of this story.",
        "note": "主人公 = main character/protagonist",
        "furigana": "これがこの<ruby>物語<rt>ものがたり</rt></ruby>の<ruby>主人公<rt>しゅじんこう</rt></ruby>ムーミントロール"
      },
      {
        "japanese": "それではさっそく物語を始めることにします",
        "english": "Now, let's promptly start the story.",
        "note": "さっそく = promptly/at once",
        "furigana": "それではさっそく<ruby>物語<rt>ものがたり</rt></ruby>を<ruby>始<rt>はじ</rt></ruby>めることにします"
      }
    ]
  },
  {
    "id": "始める",
    "word": "始める",
    "reading": "はじめる",
    "pos": "verb (ichidan)",
    "meaning": "to begin, to start",
    "notes": "Transitive. 始まる is the intransitive form.",
    "jlpt": "N5",
    "frequency": 3,
    "examples": [
      {
        "japanese": "それではさっそく物語を始めることにします",
        "english": "Now, let's promptly start the story.",
        "note": "〜ことにする (decide to)",
        "furigana": "それではさっそく<ruby>物語<rt>ものがたり</rt></ruby>を<ruby>始<rt>はじ</rt></ruby>めることにします"
      },
      {
        "japanese": "暖かい春からこの物語を始めることにしましょう",
        "english": "Let's start this story in warm spring.",
        "note": "〜ましょう (let's)",
        "furigana": "<ruby>暖<rt>あたた</rt></ruby>かい<ruby>春<rt>はる</rt></ruby>からこの<ruby>物語<rt>ものがたり</rt></ruby>を<ruby>始<rt>はじ</rt></ruby>めることにしましょう"
      }
    ]
  },
  {
    "id": "聞く",
    "word": "聞く",
    "reading": "きく",
    "pos": "verb (godan)",
    "meaning": "to hear, to listen, to ask",
    "notes": "Versatile verb. Context determines meaning.",
    "jlpt": "N5",
    "frequency": 2,
    "examples": [
      {
        "japanese": "みなさんはムーミン谷のことを聞いたことがありますか",
        "english": "Have you all heard of Moomin Valley?",
        "note": "〜たことがある (have experienced)",
        "furigana": "みなさんはムーミン<ruby>谷<rt>たに</rt></ruby>のことを<ruby>聞<rt>き</rt></ruby>いたことがありますか"
      }
    ]
  },
  {
    "id": "見る",
    "word": "見る",
    "reading": "みる",
    "pos": "verb (ichidan)",
    "meaning": "to see, to look, to watch",
    "notes": "One of the most common verbs. Te-form: 見て.",
    "jlpt": "N5",
    "frequency": 5,
    "examples": [
      {
        "japanese": "うちに行ってお姉ちゃんが帰ってきてるかどうか見てくる",
        "english": "I'm going home to see if big sister has come back.",
        "note": "〜てくる (go and come back)",
        "furigana": "うちに<ruby>行<rt>い</rt></ruby>ってお<ruby>姉<rt>ねえ</rt></ruby>ちゃんが<ruby>帰<rt>かえ</rt></ruby>ってきてるかどうか<ruby>見<rt>み</rt></ruby>てくる"
      },
      {
        "japanese": "でも見てくる",
        "english": "But I'll check.",
        "note": "見る used as 'check/verify'",
        "furigana": "でも<ruby>見<rt>み</rt></ruby>てくる"
      },
      {
        "japanese": "あなたは自分の顔鏡で見たことあるの",
        "english": "Have you ever seen your own face in the mirror?",
        "note": "〜たことある (have done before)",
        "furigana": "あなたは<ruby>自分<rt>じぶん</rt></ruby>の<ruby>顔<rt>かお</rt></ruby><ruby>鏡<rt>きょう</rt></ruby>で<ruby>見<rt>み</rt></ruby>たことあるの"
      }
    ]
  },
  {
    "id": "言う",
    "word": "言う",
    "reading": "いう",
    "pos": "verb (godan)",
    "meaning": "to say, to tell",
    "notes": "One of the most common verbs. 〜と言う (called/named).",
    "jlpt": "N5",
    "frequency": 3,
    "examples": [
      {
        "japanese": "この子は自分がムーミンだって言い張るんだよ",
        "english": "This child insists they are Moomin.",
        "note": "言い張る = to insist",
        "furigana": "この<ruby>子<rt>こ</rt></ruby>は<ruby>自分<rt>じぶん</rt></ruby>がムーミンだって<ruby>言い張<rt>いいは</rt></ruby>るんだよ"
      },
      {
        "japanese": "言ったでしょ静かにしてって",
        "english": "I told you to be quiet.",
        "note": "〜って (quotation marker, casual)",
        "furigana": "<ruby>言<rt>い</rt></ruby>ったでしょ<ruby>静<rt>しず</rt></ruby>かにしてって"
      }
    ]
  },
  {
    "id": "行く",
    "word": "行く",
    "reading": "いく",
    "pos": "verb (godan)",
    "meaning": "to go",
    "notes": "Irregular te-form: 行って. Opposite of 来る.",
    "jlpt": "N5",
    "frequency": 6,
    "examples": [
      {
        "japanese": "君もスノフキンに会いに行くの",
        "english": "Are you going to see Snufkin too?",
        "note": "〜に行く (go to do)",
        "furigana": "<ruby>君<rt>きみ</rt></ruby>もスノフキンに<ruby>会<rt>あ</rt></ruby>いに<ruby>行<rt>い</rt></ruby>くの"
      },
      {
        "japanese": "お兄さん私ムーミンのところに遊びに行っていい",
        "english": "Hey, can I go visit Moomin?",
        "note": "遊びに行く (go to play/visit)",
        "furigana": "お<ruby>兄<rt>にい</rt></ruby>さん<ruby>私<rt>わたし</rt></ruby>ムーミンのところに<ruby>遊<rt>あそ</rt></ruby>びに<ruby>行<rt>い</rt></ruby>っていい"
      },
      {
        "japanese": "去年の秋ミーのお姉ちゃんはお母さんのところへ行ったろ",
        "english": "Last autumn, my big sister went to our mother, right?",
        "note": "〜へ行く (go to a place)",
        "furigana": "<ruby>去年<rt>きょねん</rt></ruby>の<ruby>秋<rt>あき</rt></ruby>ミーのお<ruby>姉<rt>ねえ</rt></ruby>ちゃんは<ruby>お母<rt>おかあ</rt></ruby>さんのところへ<ruby>行<rt>い</rt></ruby>ったろ"
      }
    ]
  },
  {
    "id": "帰る",
    "word": "帰る",
    "reading": "かえる",
    "pos": "verb (godan)",
    "meaning": "to return, to go home",
    "notes": "Used when returning to one's home/base. Compare: 戻る.",
    "jlpt": "N5",
    "frequency": 5,
    "examples": [
      {
        "japanese": "スノフキンが帰ってる",
        "english": "Snufkin is back.",
        "note": "〜ている (resultant state)",
        "furigana": "スノフキンが<ruby>帰<rt>かえ</rt></ruby>ってる"
      },
      {
        "japanese": "今年はずいぶん早く帰ってきたね",
        "english": "You came back pretty early this year.",
        "note": "帰ってくる (come back here)",
        "furigana": "<ruby>今年<rt>ことし</rt></ruby>はずいぶん<ruby>早<rt>はや</rt></ruby>く<ruby>帰<rt>かえ</rt></ruby>ってきたね"
      },
      {
        "japanese": "ミムラが帰ってくるまでミーはずっとこの家にいていいんだよ",
        "english": "Until Mimura comes back, I can stay in this house forever.",
        "note": "〜まで (until)",
        "furigana": "ミムラが<ruby>帰<rt>かえ</rt></ruby>ってくるまでミーはずっとこの<ruby>家<rt>いえ</rt></ruby>にいていいんだよ"
      }
    ]
  },
  {
    "id": "忘れる",
    "word": "忘れる",
    "reading": "わすれる",
    "pos": "verb (ichidan)",
    "meaning": "to forget",
    "notes": "Common verb. 忘れ物 = forgotten item.",
    "jlpt": "N5",
    "frequency": 3,
    "examples": [
      {
        "japanese": "忘れちゃったの",
        "english": "Did you forget?",
        "note": "〜ちゃった (casual te-shimatta)",
        "furigana": "<ruby>忘<rt>わす</rt></ruby>れちゃったの"
      },
      {
        "japanese": "4ヶ月も眠ると去年のことなんかみんな忘れちゃうんだなミーは",
        "english": "If you sleep for four months, you forget everything from last year.",
        "note": "〜と (conditional)",
        "furigana": "4<ruby>ヶ月<rt>かげつ</rt></ruby>も<ruby>眠<rt>ねむ</rt></ruby>ると<ruby>去年<rt>きょねん</rt></ruby>のことなんかみんな<ruby>忘<rt>わす</rt></ruby>れちゃうんだなミーは"
      }
    ]
  },
  {
    "id": "思い出す",
    "word": "思い出す",
    "reading": "おもいだす",
    "pos": "verb (godan)",
    "meaning": "to remember, to recall",
    "notes": "思い (thought) + 出す (put out). To bring out a memory.",
    "jlpt": "N4",
    "frequency": 2,
    "examples": [
      {
        "japanese": "なんとなく思い出してきた",
        "english": "I'm starting to remember a little.",
        "note": "〜てきた (gradual change)",
        "furigana": "なんとなく<ruby>思い出<rt>おもいだ</rt></ruby>してきた"
      },
      {
        "japanese": "やっと思い出したらしいな",
        "english": "It seems you've finally remembered.",
        "note": "〜らしい (seems like)",
        "furigana": "やっと<ruby>思い出<rt>おもいだ</rt></ruby>したらしいな"
      }
    ]
  },
  {
    "id": "覚えている",
    "word": "覚えている",
    "reading": "おぼえている",
    "pos": "verb phrase",
    "meaning": "to remember (state)",
    "notes": "覚える = to memorize/learn. 覚えている = to remember (know).",
    "jlpt": "N4",
    "frequency": 1,
    "examples": [
      {
        "japanese": "覚えてることだってあるわ",
        "english": "There are things I remember.",
        "note": "〜だって (even)",
        "furigana": "<ruby>覚<rt>おぼ</rt></ruby>えてることだってあるわ"
      }
    ]
  },
  {
    "id": "大きい",
    "word": "大きい",
    "reading": "おおきい",
    "pos": "i-adjective",
    "meaning": "big, large",
    "notes": "Basic size adjective. Adverb form: 大きく.",
    "jlpt": "N5",
    "frequency": 3,
    "examples": [
      {
        "japanese": "ずいぶん大きいな",
        "english": "It's quite big.",
        "note": "ずいぶん = quite/considerably",
        "furigana": "ずいぶん<ruby>大<rt>おお</rt></ruby>きいな"
      },
      {
        "japanese": "これは私の帽子より大きいよ",
        "english": "This is bigger than my hat.",
        "note": "〜より (comparison)",
        "furigana": "これは<ruby>私<rt>わたし</rt></ruby>の<ruby>帽子<rt>ぼうし</rt></ruby>より<ruby>大<rt>おお</rt></ruby>きいよ"
      },
      {
        "japanese": "残念だけどこの帽子は大きすぎる",
        "english": "Unfortunately, this hat is too big.",
        "note": "〜すぎる (too much)",
        "furigana": "<ruby>残念<rt>ざんねん</rt></ruby>だけどこの<ruby>帽子<rt>ぼうし</rt></ruby>は<ruby>大<rt>おお</rt></ruby>きすぎる"
      }
    ]
  },
  {
    "id": "面白い",
    "word": "面白い",
    "reading": "おもしろい",
    "pos": "i-adjective",
    "meaning": "interesting, fun",
    "notes": "Can mean both intellectually interesting and fun/amusing.",
    "jlpt": "N5",
    "frequency": 4,
    "examples": [
      {
        "japanese": "僕たち面白いことをするんだ",
        "english": "We're going to do something fun.",
        "note": "面白いこと = something interesting",
        "furigana": "<ruby>僕<rt>ぼく</rt></ruby>たち<ruby>面白<rt>おもしろ</rt></ruby>いことをするんだ"
      },
      {
        "japanese": "山に登るのは何が面白いのさ",
        "english": "What's so fun about climbing a mountain?",
        "note": "〜のは...の (nominalizing)",
        "furigana": "<ruby>山<rt>やま</rt></ruby>に<ruby>登<rt>のぼ</rt></ruby>るのは<ruby>何<rt>なに</rt></ruby>が<ruby>面白<rt>おもしろ</rt></ruby>いのさ"
      },
      {
        "japanese": "さあスニフを起こして何か面白いことをしようよ",
        "english": "Now let's wake up Sniff and do something fun.",
        "note": "〜しよう (volitional)",
        "furigana": "さあスニフを<ruby>起<rt>お</rt></ruby>こして<ruby>何<rt>なに</rt></ruby>か<ruby>面白<rt>おもしろ</rt></ruby>いことをしようよ"
      }
    ]
  },
  {
    "id": "寂しい",
    "word": "寂しい",
    "reading": "さびしい",
    "pos": "i-adjective",
    "meaning": "lonely, lonesome",
    "notes": "Also written/pronounced さみしい. Describes emotional loneliness.",
    "jlpt": "N4",
    "frequency": 1,
    "examples": [
      {
        "japanese": "お姉ちゃんがいなくて寂しいからって冬眠する前の日ここへ来たんだぞ",
        "english": "I came here the day before hibernating because I was lonely without my sister.",
        "note": "〜からって (because, citing reason)",
        "furigana": "お<ruby>姉<rt>ねえ</rt></ruby>ちゃんがいなくて<ruby>寂<rt>さび</rt></ruby>しいからって<ruby>冬眠<rt>とうみん</rt></ruby>する<ruby>前<rt>まえ</rt></ruby>の<ruby>日<rt>ひ</rt></ruby>ここへ<ruby>来<rt>き</rt></ruby>たんだぞ"
      }
    ]
  },
  {
    "id": "暖かい",
    "word": "暖かい",
    "reading": "あたたかい",
    "pos": "i-adjective",
    "meaning": "warm",
    "notes": "For weather/temperature. Also 温かい for emotional warmth.",
    "jlpt": "N4",
    "frequency": 1,
    "examples": [
      {
        "japanese": "暖かい春からこの物語を始めることにしましょう",
        "english": "Let's start this story in warm spring.",
        "note": "暖かい modifies 春",
        "furigana": "<ruby>暖<rt>あたた</rt></ruby>かい<ruby>春<rt>はる</rt></ruby>からこの<ruby>物語<rt>ものがたり</rt></ruby>を<ruby>始<rt>はじ</rt></ruby>めることにしましょう"
      }
    ]
  },
  {
    "id": "早い",
    "word": "早い",
    "reading": "はやい",
    "pos": "i-adjective",
    "meaning": "early, fast",
    "notes": "早い (early/fast) vs 速い (speedy). Often interchangeable.",
    "jlpt": "N5",
    "frequency": 3,
    "examples": [
      {
        "japanese": "今年はずいぶん早く帰ってきたね",
        "english": "You came back pretty early this year.",
        "note": "早く (adverb form)",
        "furigana": "<ruby>今年<rt>ことし</rt></ruby>はずいぶん<ruby>早<rt>はや</rt></ruby>く<ruby>帰<rt>かえ</rt></ruby>ってきたね"
      },
      {
        "japanese": "縄梯子より階段の方が早いわ",
        "english": "It's quicker to take the stairs than the rope ladder.",
        "note": "〜より〜の方が (comparison)",
        "furigana": "<ruby>縄梯子<rt>なわばしご</rt></ruby>より<ruby>階段<rt>かいだん</rt></ruby>の<ruby>方<rt>ほう</rt></ruby>が<ruby>早<rt>はや</rt></ruby>いわ"
      },
      {
        "japanese": "パパ早くこの雲に乗って",
        "english": "Dad, quickly get on this cloud.",
        "note": "早く as adverb 'quickly'",
        "furigana": "パパ<ruby>早<rt>はや</rt></ruby>くこの<ruby>雲<rt>くも</rt></ruby>に<ruby>乗<rt>の</rt></ruby>って"
      }
    ]
  },
  {
    "id": "素晴らしい",
    "word": "素晴らしい",
    "reading": "すばらしい",
    "pos": "i-adjective",
    "meaning": "wonderful, amazing",
    "notes": "Strong positive adjective. Very common in praise.",
    "jlpt": "N4",
    "frequency": 3,
    "examples": [
      {
        "japanese": "素晴らしい眺めだろスニフ",
        "english": "It's a wonderful view, isn't it, Sniff?",
        "note": "〜だろ (right?/isn't it?)",
        "furigana": "<ruby>素晴<rt>すば</rt></ruby>らしい<ruby>眺<rt>なが</rt></ruby>めだろスニフ"
      },
      {
        "japanese": "こんな素晴らしい天気だ",
        "english": "The weather is amazing.",
        "note": "こんな = such/like this",
        "furigana": "こんな<ruby>素晴<rt>すば</rt></ruby>らしい<ruby>天気<rt>てんき</rt></ruby>だ"
      },
      {
        "japanese": "夢を追うということは素晴らしいことさ",
        "english": "Chasing a dream is a wonderful thing.",
        "note": "〜ということ (the fact that)",
        "furigana": "<ruby>夢<rt>ゆめ</rt></ruby>を<ruby>追<rt>お</rt></ruby>うということは<ruby>素晴<rt>すば</rt></ruby>らしいことさ"
      }
    ]
  },
  {
    "id": "残念",
    "word": "残念",
    "reading": "ざんねん",
    "pos": "na-adjective",
    "meaning": "unfortunate, regrettable",
    "notes": "残念ながら = unfortunately. Very common expression.",
    "jlpt": "N4",
    "frequency": 2,
    "examples": [
      {
        "japanese": "残念だけどこの帽子は大きすぎる",
        "english": "Unfortunately, this hat is too big.",
        "note": "残念だけど = unfortunately/but",
        "furigana": "<ruby>残念<rt>ざんねん</rt></ruby>だけどこの<ruby>帽子<rt>ぼうし</rt></ruby>は<ruby>大<rt>おお</rt></ruby>きすぎる"
      },
      {
        "japanese": "残念ねもっと遊びたかったのに",
        "english": "What a shame, I wanted to play more.",
        "note": "〜のに (even though)",
        "furigana": "<ruby>残念<rt>ざんねん</rt></ruby>ねもっと<ruby>遊<rt>あそ</rt></ruby>びたかったのに"
      }
    ]
  },
  {
    "id": "本当",
    "word": "本当",
    "reading": "ほんとう",
    "pos": "noun/na-adj",
    "meaning": "truth, really",
    "notes": "本当に = really. 本当？ = Really? Very common.",
    "jlpt": "N5",
    "frequency": 4,
    "examples": [
      {
        "japanese": "本当に空飛ぶ船なんかできるのかな",
        "english": "I wonder if a real flying ship can be made.",
        "note": "本当に = really",
        "furigana": "<ruby>本当<rt>ほんとう</rt></ruby>に<ruby>空<rt>そら</rt></ruby><ruby>飛<rt>と</rt></ruby>ぶ<ruby>船<rt>ふね</rt></ruby>なんかできるのかな"
      },
      {
        "japanese": "僕本当にムーミンなんだよ",
        "english": "I'm really Moomin!",
        "note": "なんだよ = emphatic explanation",
        "furigana": "<ruby>僕<rt>ぼく</rt></ruby><ruby>本当<rt>ほんとう</rt></ruby>にムーミンなんだよ"
      },
      {
        "japanese": "ねえ本当にあんた誰",
        "english": "Hey, who are you really?",
        "note": "本当に as emphasis",
        "furigana": "ねえ<ruby>本当<rt>ほんとう</rt></ruby>にあんた<ruby>誰<rt>だれ</rt></ruby>"
      }
    ]
  },
  {
    "id": "お姉ちゃん",
    "word": "お姉ちゃん",
    "reading": "おねえちゃん",
    "pos": "noun",
    "meaning": "big sister (informal)",
    "notes": "Casual form. More formal: お姉さん (oneesan).",
    "jlpt": "N5",
    "frequency": 8,
    "examples": [
      {
        "japanese": "私家でお姉ちゃんと一緒に寝てたはずだけど",
        "english": "I should have been sleeping with my big sister at home.",
        "note": "〜と一緒に (together with)",
        "furigana": "<ruby>私家<rt>しか</rt></ruby>でお<ruby>姉<rt>ねえ</rt></ruby>ちゃんと<ruby>一緒<rt>いっしょ</rt></ruby>に<ruby>寝<rt>ね</rt></ruby>てたはずだけど"
      },
      {
        "japanese": "去年の秋ミーのお姉ちゃんはお母さんのところへ行ったろ",
        "english": "Last autumn, Little My's big sister went to their mother.",
        "note": "ミーの (Little My's)",
        "furigana": "<ruby>去年<rt>きょねん</rt></ruby>の<ruby>秋<rt>あき</rt></ruby>ミーのお<ruby>姉<rt>ねえ</rt></ruby>ちゃんは<ruby>お母<rt>おかあ</rt></ruby>さんのところへ<ruby>行<rt>い</rt></ruby>ったろ"
      },
      {
        "japanese": "うちに行ってお姉ちゃんが帰ってきてるかどうか見てくる",
        "english": "I'm going home to see if big sister has come back.",
        "note": "〜かどうか (whether or not)",
        "furigana": "うちに<ruby>行<rt>い</rt></ruby>ってお<ruby>姉<rt>ねえ</rt></ruby>ちゃんが<ruby>帰<rt>かえ</rt></ruby>ってきてるかどうか<ruby>見<rt>み</rt></ruby>てくる"
      }
    ]
  },
  {
    "id": "お兄さん",
    "word": "お兄さん",
    "reading": "おにいさん",
    "pos": "noun",
    "meaning": "big brother",
    "notes": "Casual: お兄ちゃん. Used for one's own brother or addressing young men.",
    "jlpt": "N5",
    "frequency": 4,
    "examples": [
      {
        "japanese": "お兄さん私ムーミンのところに遊びに行っていい",
        "english": "Hey, can I go visit Moomin?",
        "note": "Asking brother for permission",
        "furigana": "お<ruby>兄<rt>にい</rt></ruby>さん<ruby>私<rt>わたし</rt></ruby>ムーミンのところに<ruby>遊<rt>あそ</rt></ruby>びに<ruby>行<rt>い</rt></ruby>っていい"
      },
      {
        "japanese": "もちろんお兄さんは行かないわね",
        "english": "Of course, big brother isn't going.",
        "note": "わね (female sentence ending)",
        "furigana": "もちろんお<ruby>兄<rt>にい</rt></ruby>さんは<ruby>行<rt>い</rt></ruby>かないわね"
      }
    ]
  },
  {
    "id": "パパ",
    "word": "パパ",
    "reading": "パパ",
    "pos": "noun",
    "meaning": "papa, dad",
    "notes": "Katakana word from English. ムーミンパパ = Moominpapa.",
    "jlpt": "N5",
    "frequency": 8,
    "examples": [
      {
        "japanese": "そしてこれがムーミンパパ",
        "english": "And this is Moomin Papa.",
        "note": "Character introduction",
        "furigana": "そしてこれがムーミンパパ"
      },
      {
        "japanese": "この帽子パパのに似てるな",
        "english": "This hat looks a lot like Dad's.",
        "note": "パパの = Dad's (possessive)",
        "furigana": "この<ruby>帽子<rt>ぼうし</rt></ruby>パパのに<ruby>似<rt>に</rt></ruby>てるな"
      },
      {
        "japanese": "どうしたのパパ",
        "english": "What's wrong, Dad?",
        "note": "どうしたの = What happened?",
        "furigana": "どうしたのパパ"
      }
    ]
  },
  {
    "id": "ママ",
    "word": "ママ",
    "reading": "ママ",
    "pos": "noun",
    "meaning": "mama, mom",
    "notes": "Katakana word from English. ムーミンママ = Moominmama.",
    "jlpt": "N5",
    "frequency": 10,
    "examples": [
      {
        "japanese": "これがムーミンママ",
        "english": "This is Moomin Mama.",
        "note": "Character introduction",
        "furigana": "これがムーミンママ"
      },
      {
        "japanese": "きっとムーミンママが何かおいしいものを作ってるんだね",
        "english": "Moominmama is probably making something delicious.",
        "note": "きっと = surely/probably",
        "furigana": "きっとムーミンママが<ruby>何<rt>なに</rt></ruby>かおいしいものを<ruby>作<rt>つく</rt></ruby>ってるんだね"
      },
      {
        "japanese": "僕をムーミンって呼んでよママ",
        "english": "Call me Moomin, Mama.",
        "note": "〜って呼ぶ (to call by name)",
        "furigana": "<ruby>僕<rt>ぼく</rt></ruby>をムーミンって<ruby>呼<rt>よ</rt></ruby>んでよママ"
      }
    ]
  },
  {
    "id": "今年",
    "word": "今年",
    "reading": "ことし",
    "pos": "noun",
    "meaning": "this year",
    "notes": "今 (now) + 年 (year). Compare: 去年 (last year), 来年 (next year).",
    "jlpt": "N5",
    "frequency": 4,
    "examples": [
      {
        "japanese": "今年はずいぶん早く帰ってきたね",
        "english": "You came back pretty early this year.",
        "note": "ずいぶん = considerably",
        "furigana": "<ruby>今年<rt>ことし</rt></ruby>はずいぶん<ruby>早<rt>はや</rt></ruby>く<ruby>帰<rt>かえ</rt></ruby>ってきたね"
      },
      {
        "japanese": "今年あの山に登るのは僕たちが一番なんだぜ",
        "english": "This year, we're the first ones to climb that mountain.",
        "note": "一番 = first/best",
        "furigana": "<ruby>今年<rt>ことし</rt></ruby>あの<ruby>山<rt>やま</rt></ruby>に<ruby>登<rt>のぼ</rt></ruby>るのは<ruby>僕<rt>ぼく</rt></ruby>たちが<ruby>一番<rt>いちばん</rt></ruby>なんだぜ"
      },
      {
        "japanese": "今年こそ僕は空飛ぶ船を作ってみせるぞ",
        "english": "This year, I will definitely make a flying ship!",
        "note": "こそ = emphasis (this year for sure)",
        "furigana": "<ruby>今年<rt>ことし</rt></ruby>こそ<ruby>僕<rt>ぼく</rt></ruby>は<ruby>空<rt>そら</rt></ruby><ruby>飛<rt>と</rt></ruby>ぶ<ruby>船<rt>ふね</rt></ruby>を<ruby>作<rt>つく</rt></ruby>ってみせるぞ"
      }
    ]
  },
  {
    "id": "去年",
    "word": "去年",
    "reading": "きょねん",
    "pos": "noun",
    "meaning": "last year",
    "notes": "去 (go away) + 年 (year). The year that has passed.",
    "jlpt": "N5",
    "frequency": 2,
    "examples": [
      {
        "japanese": "去年の秋ミーのお姉ちゃんはお母さんのところへ行ったろ",
        "english": "Last autumn, Little My's big sister went to their mother.",
        "note": "去年の秋 = last autumn",
        "furigana": "<ruby>去年<rt>きょねん</rt></ruby>の<ruby>秋<rt>あき</rt></ruby>ミーのお<ruby>姉<rt>ねえ</rt></ruby>ちゃんは<ruby>お母<rt>おかあ</rt></ruby>さんのところへ<ruby>行<rt>い</rt></ruby>ったろ"
      },
      {
        "japanese": "4ヶ月も眠ると去年のことなんかみんな忘れちゃうんだな",
        "english": "If you sleep for four months, you forget everything from last year.",
        "note": "去年のこと = things from last year",
        "furigana": "4<ruby>ヶ月<rt>かげつ</rt></ruby>も<ruby>眠<rt>ねむ</rt></ruby>ると<ruby>去年<rt>きょねん</rt></ruby>のことなんかみんな<ruby>忘<rt>わす</rt></ruby>れちゃうんだな"
      }
    ]
  },
  {
    "id": "山",
    "word": "山",
    "reading": "やま",
    "pos": "noun",
    "meaning": "mountain",
    "notes": "Basic noun. 山に登る = to climb a mountain.",
    "jlpt": "N5",
    "frequency": 3,
    "examples": [
      {
        "japanese": "山に登るのは何が面白いのさ",
        "english": "What's so fun about climbing a mountain?",
        "note": "山に登る (climb a mountain)",
        "furigana": "<ruby>山<rt>やま</rt></ruby>に<ruby>登<rt>のぼ</rt></ruby>るのは<ruby>何<rt>なに</rt></ruby>が<ruby>面白<rt>おもしろ</rt></ruby>いのさ"
      },
      {
        "japanese": "今年あの山に登るのは僕たちが一番なんだぜ",
        "english": "This year, we're the first ones to climb that mountain.",
        "note": "あの山 = that mountain",
        "furigana": "<ruby>今年<rt>ことし</rt></ruby>あの<ruby>山<rt>やま</rt></ruby>に<ruby>登<rt>のぼ</rt></ruby>るのは<ruby>僕<rt>ぼく</rt></ruby>たちが<ruby>一番<rt>いちばん</rt></ruby>なんだぜ"
      }
    ]
  },
  {
    "id": "海",
    "word": "海",
    "reading": "うみ",
    "pos": "noun",
    "meaning": "sea, ocean",
    "notes": "Basic noun. 海へ行く = to go to the beach/sea.",
    "jlpt": "N5",
    "frequency": 2,
    "examples": [
      {
        "japanese": "海が光ってる",
        "english": "The sea is sparkling.",
        "note": "〜ている (continuous state)",
        "furigana": "<ruby>海<rt>うみ</rt></ruby>が<ruby>光<rt>ひか</rt></ruby>ってる"
      },
      {
        "japanese": "海だってね",
        "english": "And the sea too.",
        "note": "だって = also/even",
        "furigana": "<ruby>海<rt>うみ</rt></ruby>だってね"
      }
    ]
  },
  {
    "id": "雲",
    "word": "雲",
    "reading": "くも",
    "pos": "noun",
    "meaning": "cloud",
    "notes": "Appears in the magic hat scene where clouds form from the hat.",
    "jlpt": "N4",
    "frequency": 5,
    "examples": [
      {
        "japanese": "何これ雲みたい",
        "english": "What is this? It looks like a cloud.",
        "note": "〜みたい (looks like)",
        "furigana": "<ruby>何<rt>なに</rt></ruby>これ<ruby>雲<rt>くも</rt></ruby>みたい"
      },
      {
        "japanese": "僕も知らないようちの中から雲が湧いてきたんだ",
        "english": "I don't know either, a cloud has emerged from inside our house.",
        "note": "湧いてきた = emerged/sprung up",
        "furigana": "<ruby>僕<rt>ぼく</rt></ruby>も<ruby>知<rt>し</rt></ruby>らないようちの<ruby>中<rt>なか</rt></ruby>から<ruby>雲<rt>くも</rt></ruby>が<ruby>湧<rt>わ</rt></ruby>いてきたんだ"
      },
      {
        "japanese": "あらららら雲がなくなっちゃった",
        "english": "Oh dear, the cloud has disappeared.",
        "note": "なくなる = to disappear",
        "furigana": "あらららら<ruby>雲<rt>くも</rt></ruby>がなくなっちゃった"
      }
    ]
  },
  {
    "id": "旅",
    "word": "旅",
    "reading": "たび",
    "pos": "noun",
    "meaning": "trip, journey",
    "notes": "旅行 (りょこう) is more common for 'travel'. 旅 is more poetic.",
    "jlpt": "N4",
    "frequency": 2,
    "examples": [
      {
        "japanese": "南の方の旅はつまらなかったの",
        "english": "Was the trip to the south boring?",
        "note": "南の方 = the south",
        "furigana": "<ruby>南<rt>みなみ</rt></ruby>の<ruby>方<rt>ほう</rt></ruby>の<ruby>旅<rt>たび</rt></ruby>はつまらなかったの"
      },
      {
        "japanese": "旅の話をしてよ",
        "english": "Tell me about your trip.",
        "note": "旅の話 = stories of the trip",
        "furigana": "<ruby>旅<rt>たび</rt></ruby>の<ruby>話<rt>はなし</rt></ruby>をしてよ"
      }
    ]
  },
  {
    "id": "話",
    "word": "話",
    "reading": "はなし",
    "pos": "noun",
    "meaning": "story, talk, conversation",
    "notes": "話す (to speak) → 話 (talk/story). Very common word.",
    "jlpt": "N5",
    "frequency": 2,
    "examples": [
      {
        "japanese": "旅の話をしてよ",
        "english": "Tell me about your trip.",
        "note": "話をする = to tell/talk about",
        "furigana": "<ruby>旅<rt>たび</rt></ruby>の<ruby>話<rt>はなし</rt></ruby>をしてよ"
      },
      {
        "japanese": "あとでゆっくりとね",
        "english": "Later, slowly.",
        "note": "Response to request for stories",
        "furigana": "あとでゆっくりとね"
      }
    ]
  },
  {
    "id": "夢",
    "word": "夢",
    "reading": "ゆめ",
    "pos": "noun",
    "meaning": "dream",
    "notes": "Both sleep dreams and life dreams/aspirations.",
    "jlpt": "N4",
    "frequency": 4,
    "examples": [
      {
        "japanese": "夢ね兄さんは夢を追ってるんだわ",
        "english": "A dream, huh? You're chasing a dream, brother.",
        "note": "夢を追う = to chase a dream",
        "furigana": "<ruby>夢<rt>ゆめ</rt></ruby>ね<ruby>兄<rt>にい</rt></ruby>さんは<ruby>夢<rt>ゆめ</rt></ruby>を<ruby>追<rt>お</rt></ruby>ってるんだわ"
      },
      {
        "japanese": "夢を追うということは素晴らしいことさ",
        "english": "Chasing a dream is a wonderful thing.",
        "note": "〜ということ (the fact that)",
        "furigana": "<ruby>夢<rt>ゆめ</rt></ruby>を<ruby>追<rt>お</rt></ruby>うということは<ruby>素晴<rt>すば</rt></ruby>らしいことさ"
      },
      {
        "japanese": "僕食べ物の夢ならしょっちゅう見るよ",
        "english": "Well, I often dream about food.",
        "note": "夢を見る = to have a dream",
        "furigana": "<ruby>僕<rt>ぼく</rt></ruby><ruby>食べ物<rt>たべもの</rt></ruby>の<ruby>夢<rt>ゆめ</rt></ruby>ならしょっちゅう<ruby>見<rt>み</rt></ruby>るよ"
      }
    ]
  },
  {
    "id": "船",
    "word": "船",
    "reading": "ふね",
    "pos": "noun",
    "meaning": "ship, boat",
    "notes": "空飛ぶ船 = flying ship appears in Snorkmaiden's brother's dream.",
    "jlpt": "N4",
    "frequency": 2,
    "examples": [
      {
        "japanese": "今年こそ僕は空飛ぶ船を作ってみせるぞ",
        "english": "This year, I will definitely make a flying ship!",
        "note": "空飛ぶ = sky-flying",
        "furigana": "<ruby>今年<rt>ことし</rt></ruby>こそ<ruby>僕<rt>ぼく</rt></ruby>は<ruby>空<rt>そら</rt></ruby><ruby>飛<rt>と</rt></ruby>ぶ<ruby>船<rt>ふね</rt></ruby>を<ruby>作<rt>つく</rt></ruby>ってみせるぞ"
      },
      {
        "japanese": "本当に空飛ぶ船なんかできるのかな",
        "english": "I wonder if a real flying ship can be made.",
        "note": "〜かな = I wonder if",
        "furigana": "<ruby>本当<rt>ほんとう</rt></ruby>に<ruby>空<rt>そら</rt></ruby><ruby>飛<rt>と</rt></ruby>ぶ<ruby>船<rt>ふね</rt></ruby>なんかできるのかな"
      }
    ]
  },
  {
    "id": "作る",
    "word": "作る",
    "reading": "つくる",
    "pos": "verb (godan)",
    "meaning": "to make, to create",
    "notes": "Very versatile. Used for food, things, situations.",
    "jlpt": "N5",
    "frequency": 3,
    "examples": [
      {
        "japanese": "冬眠明けのお料理を作ることにしましょうか",
        "english": "Shall we make some post-hibernation dishes?",
        "note": "〜ことにする (decide to)",
        "furigana": "<ruby>冬眠<rt>とうみん</rt></ruby><ruby>明<rt>あ</rt></ruby>けのお<ruby>料理<rt>りょうり</rt></ruby>を<ruby>作<rt>つく</rt></ruby>ることにしましょうか"
      },
      {
        "japanese": "今年こそ僕は空飛ぶ船を作ってみせるぞ",
        "english": "This year, I will definitely make a flying ship!",
        "note": "〜てみせる (will show by doing)",
        "furigana": "<ruby>今年<rt>ことし</rt></ruby>こそ<ruby>僕<rt>ぼく</rt></ruby>は<ruby>空<rt>そら</rt></ruby><ruby>飛<rt>と</rt></ruby>ぶ<ruby>船<rt>ふね</rt></ruby>を<ruby>作<rt>つく</rt></ruby>ってみせるぞ"
      },
      {
        "japanese": "きっとムーミンママが何かおいしいものを作ってるんだね",
        "english": "Moominmama is probably making something delicious.",
        "note": "何か = something",
        "furigana": "きっとムーミンママが<ruby>何<rt>なに</rt></ruby>かおいしいものを<ruby>作<rt>つく</rt></ruby>ってるんだね"
      }
    ]
  },
  {
    "id": "乗る",
    "word": "乗る",
    "reading": "のる",
    "pos": "verb (godan)",
    "meaning": "to ride, to get on",
    "notes": "Used for vehicles, horses, etc. 〜に乗る pattern.",
    "jlpt": "N5",
    "frequency": 4,
    "examples": [
      {
        "japanese": "私も乗りたい",
        "english": "I want to ride it too.",
        "note": "〜たい (want to)",
        "furigana": "<ruby>私<rt>わたし</rt></ruby>も<ruby>乗<rt>の</rt></ruby>りたい"
      },
      {
        "japanese": "パパ早くこの雲に乗って",
        "english": "Dad, quickly get on this cloud.",
        "note": "〜に乗る (get on)",
        "furigana": "パパ<ruby>早<rt>はや</rt></ruby>くこの<ruby>雲<rt>くも</rt></ruby>に<ruby>乗<rt>の</rt></ruby>って"
      },
      {
        "japanese": "どうしたの乗りたければ乗せてあげるよ",
        "english": "What's wrong? If you want to ride, I can let you.",
        "note": "〜ば (conditional)",
        "furigana": "どうしたの<ruby>乗<rt>の</rt></ruby>りたければ<ruby>乗<rt>の</rt></ruby>せてあげるよ"
      }
    ]
  },
  {
    "id": "飛ぶ",
    "word": "飛ぶ",
    "reading": "とぶ",
    "pos": "verb (godan)",
    "meaning": "to fly, to jump",
    "notes": "Used for birds, planes, jumping. 空を飛ぶ = fly in the sky.",
    "jlpt": "N4",
    "frequency": 2,
    "examples": [
      {
        "japanese": "子供たちのこと知ってるか空中を飛び回っているんだぞ",
        "english": "Do you know about the kids? They are flying around in the air!",
        "note": "飛び回る = fly around",
        "furigana": "<ruby>子供<rt>こども</rt></ruby>たちのこと<ruby>知<rt>し</rt></ruby>ってるか<ruby>空中<rt>くうちゅう</rt></ruby>を<ruby>飛び回<rt>とびまわ</rt></ruby>っているんだぞ"
      },
      {
        "japanese": "ねえスナフキンさっき飛行鬼が飛んでるのを見たよ",
        "english": "Hey Snufkin, I saw a flying goblin earlier.",
        "note": "飛行鬼 = The Hobgoblin",
        "furigana": "ねえスナフキンさっき<ruby>飛行<rt>ひこう</rt></ruby><ruby>鬼<rt>おに</rt></ruby>が<ruby>飛<rt>と</rt></ruby>んでるのを<ruby>見<rt>み</rt></ruby>たよ"
      }
    ]
  },
  {
    "id": "落ちる",
    "word": "落ちる",
    "reading": "おちる",
    "pos": "verb (ichidan)",
    "meaning": "to fall, to drop",
    "notes": "Intransitive. Transitive: 落とす (to drop something).",
    "jlpt": "N4",
    "frequency": 3,
    "examples": [
      {
        "japanese": "落っこちないように気をつけなさいって",
        "english": "Be careful not to fall.",
        "note": "落っこちる = casual for 落ちる",
        "furigana": "<ruby>落<rt>お</rt></ruby>っこちないように<ruby>気<rt>き</rt></ruby>をつけなさいって"
      },
      {
        "japanese": "落ちる落ちる死んじゃう",
        "english": "I'm falling, I'm falling, I'm going to die!",
        "note": "Repeated for emphasis/panic",
        "furigana": "<ruby>落<rt>お</rt></ruby>ちる<ruby>落<rt>お</rt></ruby>ちる<ruby>死<rt>し</rt></ruby>んじゃう"
      }
    ]
  },
  {
    "id": "登る",
    "word": "登る",
    "reading": "のぼる",
    "pos": "verb (godan)",
    "meaning": "to climb",
    "notes": "山に登る = climb a mountain. 上る is similar but broader.",
    "jlpt": "N4",
    "frequency": 2,
    "examples": [
      {
        "japanese": "山に登るのは何が面白いのさ",
        "english": "What's so fun about climbing a mountain?",
        "note": "〜に登る (climb onto)",
        "furigana": "<ruby>山<rt>やま</rt></ruby>に<ruby>登<rt>のぼ</rt></ruby>るのは<ruby>何<rt>なに</rt></ruby>が<ruby>面白<rt>おもしろ</rt></ruby>いのさ"
      },
      {
        "japanese": "今年あの山に登るのは僕たちが一番なんだぜ",
        "english": "This year, we're the first ones to climb that mountain.",
        "note": "登るのは = climbing is",
        "furigana": "<ruby>今年<rt>ことし</rt></ruby>あの<ruby>山<rt>やま</rt></ruby>に<ruby>登<rt>のぼ</rt></ruby>るのは<ruby>僕<rt>ぼく</rt></ruby>たちが<ruby>一番<rt>いちばん</rt></ruby>なんだぜ"
      }
    ]
  },
  {
    "id": "遊ぶ",
    "word": "遊ぶ",
    "reading": "あそぶ",
    "pos": "verb (godan)",
    "meaning": "to play",
    "notes": "General play. 遊びに行く = go to play/visit someone.",
    "jlpt": "N5",
    "frequency": 4,
    "examples": [
      {
        "japanese": "お兄さん私ムーミンのところに遊びに行っていい",
        "english": "Hey, can I go visit Moomin?",
        "note": "遊びに行く (go to play/visit)",
        "furigana": "お<ruby>兄<rt>にい</rt></ruby>さん<ruby>私<rt>わたし</rt></ruby>ムーミンのところに<ruby>遊<rt>あそ</rt></ruby>びに<ruby>行<rt>い</rt></ruby>っていい"
      },
      {
        "japanese": "残念ねもっと遊びたかったのに",
        "english": "What a shame, I wanted to play more.",
        "note": "〜たかった (wanted to)",
        "furigana": "<ruby>残念<rt>ざんねん</rt></ruby>ねもっと<ruby>遊<rt>あそ</rt></ruby>びたかったのに"
      },
      {
        "japanese": "また一緒に遊ぼうさあおいで",
        "english": "Let's play together again, come on over.",
        "note": "〜よう (volitional)",
        "furigana": "また<ruby>一緒<rt>いっしょ</rt></ruby>に<ruby>遊<rt>あそ</rt></ruby>ぼうさあおいで"
      }
    ]
  },
  {
    "id": "探す",
    "word": "探す",
    "reading": "さがす",
    "pos": "verb (godan)",
    "meaning": "to search, to look for",
    "notes": "探す (look for) vs 見つける (find). Common pair.",
    "jlpt": "N4",
    "frequency": 2,
    "examples": [
      {
        "japanese": "地下室は探したの",
        "english": "Did you search the basement?",
        "note": "Past tense question",
        "furigana": "<ruby>地下<rt>ちか</rt></ruby><ruby>室<rt>しつ</rt></ruby>は<ruby>探<rt>さが</rt></ruby>したの"
      },
      {
        "japanese": "きっとあの帽子を探しているんだよ",
        "english": "I'm sure it's looking for that hat.",
        "note": "〜ている (progressive)",
        "furigana": "きっとあの<ruby>帽子<rt>ぼうし</rt></ruby>を<ruby>探<rt>さが</rt></ruby>しているんだよ"
      }
    ]
  },
  {
    "id": "見つかる",
    "word": "見つかる",
    "reading": "みつかる",
    "pos": "verb (godan)",
    "meaning": "to be found",
    "notes": "Intransitive. Transitive: 見つける (to find).",
    "jlpt": "N4",
    "frequency": 3,
    "examples": [
      {
        "japanese": "見つかった",
        "english": "Found it.",
        "note": "Past tense = 'it was found'",
        "furigana": "<ruby>見<rt>み</rt></ruby>つかった"
      },
      {
        "japanese": "ムーミンがどうしても見つからないんです",
        "english": "I just can't find Moomin.",
        "note": "どうしても〜ない (no matter what)",
        "furigana": "ムーミンがどうしても<ruby>見<rt>み</rt></ruby>つからないんです"
      },
      {
        "japanese": "どうやら僕だけ見つからなかったようだね",
        "english": "It seems I'm the only one who wasn't found.",
        "note": "〜ようだ (it seems)",
        "furigana": "どうやら<ruby>僕<rt>ぼく</rt></ruby>だけ<ruby>見<rt>み</rt></ruby>つからなかったようだね"
      }
    ]
  },
  {
    "id": "隠れる",
    "word": "隠れる",
    "reading": "かくれる",
    "pos": "verb (ichidan)",
    "meaning": "to hide (oneself)",
    "notes": "Intransitive. かくれんぼ = hide and seek.",
    "jlpt": "N4",
    "frequency": 3,
    "examples": [
      {
        "japanese": "あのどこか隠れるところありませんか",
        "english": "Is there anywhere to hide?",
        "note": "隠れるところ = place to hide",
        "furigana": "あのどこか<ruby>隠<rt>かく</rt></ruby>れるところありませんか"
      },
      {
        "japanese": "君はムーミンがどこに隠れているか知っているのかい",
        "english": "Do you know where Moomin is hiding?",
        "note": "〜ているか (whether ~ing)",
        "furigana": "<ruby>君<rt>きみ</rt></ruby>はムーミンがどこに<ruby>隠<rt>かく</rt></ruby>れているか<ruby>知<rt>し</rt></ruby>っているのかい"
      }
    ]
  },
  {
    "id": "知る",
    "word": "知る",
    "reading": "しる",
    "pos": "verb (godan)",
    "meaning": "to know",
    "notes": "知っている = know (state). 知らない = don't know.",
    "jlpt": "N5",
    "frequency": 5,
    "examples": [
      {
        "japanese": "僕も知らないよ",
        "english": "I don't know either.",
        "note": "知らない = don't know",
        "furigana": "<ruby>僕<rt>ぼく</rt></ruby>も<ruby>知<rt>し</rt></ruby>らないよ"
      },
      {
        "japanese": "おい知らないぞ落ちたって知らないぞ",
        "english": "Hey, I don't know! If you fall, it's not my problem!",
        "note": "知らない = 'not my problem'",
        "furigana": "おい<ruby>知<rt>し</rt></ruby>らないぞ<ruby>落<rt>お</rt></ruby>ちたって<ruby>知<rt>し</rt></ruby>らないぞ"
      },
      {
        "japanese": "子供たちのこと知ってるか",
        "english": "Do you know about the kids?",
        "note": "知ってる = know (casual)",
        "furigana": "<ruby>子供<rt>こども</rt></ruby>たちのこと<ruby>知<rt>し</rt></ruby>ってるか"
      }
    ]
  },
  {
    "id": "分かる",
    "word": "分かる",
    "reading": "わかる",
    "pos": "verb (godan)",
    "meaning": "to understand, to know",
    "notes": "分かった = understood/got it. Very common response.",
    "jlpt": "N5",
    "frequency": 2,
    "examples": [
      {
        "japanese": "分かったわ分かったから少し黙って落ち着いてちょうだい",
        "english": "I understand, I understand, so be quiet and calm down a little.",
        "note": "分かった = understood",
        "furigana": "<ruby>分<rt>わ</rt></ruby>かったわ<ruby>分<rt>わ</rt></ruby>かったから<ruby>少<rt>すこ</rt></ruby>し<ruby>黙<rt>だま</rt></ruby>って<ruby>落ち着<rt>おちつ</rt></ruby>いてちょうだい"
      },
      {
        "japanese": "ママのこと分かってるんでしょ",
        "english": "You know who Mama is, right?",
        "note": "分かってる = you know/understand",
        "furigana": "ママのこと<ruby>分<rt>わ</rt></ruby>かってるんでしょ"
      }
    ]
  },
  {
    "id": "待つ",
    "word": "待つ",
    "reading": "まつ",
    "pos": "verb (godan)",
    "meaning": "to wait",
    "notes": "〜を待つ = wait for. ちょっと待って = wait a moment.",
    "jlpt": "N5",
    "frequency": 2,
    "examples": [
      {
        "japanese": "おい待て降りてこい",
        "english": "Hey, wait, come down!",
        "note": "待て = imperative (wait!)",
        "furigana": "おい<ruby>待<rt>ま</rt></ruby>て<ruby>降<rt>お</rt></ruby>りてこい"
      },
      {
        "japanese": "おい待て僕の雲待ってくれ",
        "english": "Hey wait, my cloud, wait for me!",
        "note": "待ってくれ = please wait",
        "furigana": "おい<ruby>待<rt>ま</rt></ruby>て<ruby>僕<rt>ぼく</rt></ruby>の<ruby>雲<rt>くも</rt></ruby><ruby>待<rt>ま</rt></ruby>ってくれ"
      }
    ]
  },
  {
    "id": "呼ぶ",
    "word": "呼ぶ",
    "reading": "よぶ",
    "pos": "verb (godan)",
    "meaning": "to call",
    "notes": "〜と呼ぶ = to call (by name). 呼んで = call me.",
    "jlpt": "N4",
    "frequency": 3,
    "examples": [
      {
        "japanese": "ムーミンって呼んで",
        "english": "Call me Moomin.",
        "note": "〜って呼ぶ (call someone ~)",
        "furigana": "ムーミンって<ruby>呼<rt>よ</rt></ruby>んで"
      },
      {
        "japanese": "どうして僕のこと呼んでくれないの",
        "english": "Why won't you call me?",
        "note": "〜てくれない (won't do for me)",
        "furigana": "どうして<ruby>僕<rt>ぼく</rt></ruby>のこと<ruby>呼<rt>よ</rt></ruby>んでくれないの"
      }
    ]
  },
  {
    "id": "捨てる",
    "word": "捨てる",
    "reading": "すてる",
    "pos": "verb (ichidan)",
    "meaning": "to throw away, to discard",
    "notes": "Common verb for disposing of things. ゴミを捨てる = throw away trash.",
    "jlpt": "N4",
    "frequency": 2,
    "examples": [
      {
        "japanese": "それじゃあ捨てちゃおうか",
        "english": "Then shall we throw it away?",
        "note": "〜ちゃう = casual 〜てしまう",
        "furigana": "それじゃあ<ruby>捨<rt>す</rt></ruby>てちゃおうか"
      },
      {
        "japanese": "拾ったものを捨てただけさ",
        "english": "I just threw away what I picked up.",
        "note": "拾う = to pick up",
        "furigana": "<ruby>拾<rt>ひろ</rt></ruby>ったものを<ruby>捨<rt>す</rt></ruby>てただけさ"
      }
    ]
  },
  {
    "id": "僕",
    "word": "僕",
    "reading": "ぼく",
    "pos": "pronoun",
    "meaning": "I, me (male)",
    "notes": "Masculine first person. Used by boys and some adult men.",
    "jlpt": "N5",
    "frequency": 25,
    "examples": [
      {
        "japanese": "僕はムーミントロール",
        "english": "I'm Moomintroll.",
        "note": "Self-introduction",
        "furigana": "<ruby>僕<rt>ぼく</rt></ruby>はムーミントロール"
      },
      {
        "japanese": "僕たち面白いことをするんだ",
        "english": "We're going to do something fun.",
        "note": "僕たち = we (male speaker)",
        "furigana": "<ruby>僕<rt>ぼく</rt></ruby>たち<ruby>面白<rt>おもしろ</rt></ruby>いことをするんだ"
      },
      {
        "japanese": "僕本当にムーミンなんだよ",
        "english": "I'm really Moomin!",
        "note": "Emphatic statement",
        "furigana": "<ruby>僕<rt>ぼく</rt></ruby><ruby>本当<rt>ほんとう</rt></ruby>にムーミンなんだよ"
      }
    ]
  },
  {
    "id": "私",
    "word": "私",
    "reading": "わたし",
    "pos": "pronoun",
    "meaning": "I, me",
    "notes": "Neutral/feminine first person. Most common for women.",
    "jlpt": "N5",
    "frequency": 8,
    "examples": [
      {
        "japanese": "私どうしてこの家で冬眠してたの",
        "english": "Why was I hibernating in this house?",
        "note": "Little My speaking",
        "furigana": "<ruby>私<rt>わたし</rt></ruby>どうしてこの<ruby>家<rt>いえ</rt></ruby>で<ruby>冬眠<rt>とうみん</rt></ruby>してたの"
      },
      {
        "japanese": "私も乗りたい",
        "english": "I want to ride it too.",
        "note": "私も = me too",
        "furigana": "<ruby>私<rt>わたし</rt></ruby>も<ruby>乗<rt>の</rt></ruby>りたい"
      },
      {
        "japanese": "私が自分の子供を間違えるはずはありません",
        "english": "I would never mistake my own child.",
        "note": "Moominmama speaking",
        "furigana": "<ruby>私<rt>わたし</rt></ruby>が<ruby>自分<rt>じぶん</rt></ruby>の<ruby>子供<rt>こども</rt></ruby>を<ruby>間違<rt>まちが</rt></ruby>えるはずはありません"
      }
    ]
  },
  {
    "id": "みんな",
    "word": "みんな",
    "reading": "みんな",
    "pos": "pronoun",
    "meaning": "everyone, all",
    "notes": "Informal. More formal: 皆さん (minasan).",
    "jlpt": "N5",
    "frequency": 5,
    "examples": [
      {
        "japanese": "ほらみんな眠っていますよ",
        "english": "Look, everyone is sleeping.",
        "note": "みんな as subject",
        "furigana": "ほらみんな<ruby>眠<rt>ねむ</rt></ruby>っていますよ"
      },
      {
        "japanese": "みなさんはムーミン谷のことを聞いたことがありますか",
        "english": "Have you all heard of Moomin Valley?",
        "note": "みなさん = polite 'everyone'",
        "furigana": "みなさんはムーミン<ruby>谷<rt>たに</rt></ruby>のことを<ruby>聞<rt>き</rt></ruby>いたことがありますか"
      },
      {
        "japanese": "さあさあみんなお食事しましょうね",
        "english": "Alright everyone, let's have a meal.",
        "note": "Addressing a group",
        "furigana": "さあさあみんなお<ruby>食事<rt>しょくじ</rt></ruby>しましょうね"
      }
    ]
  },
  {
    "id": "ここ",
    "word": "ここ",
    "reading": "ここ",
    "pos": "pronoun",
    "meaning": "here, this place",
    "notes": "Location demonstrative. ここ/そこ/あそこ (here/there/over there).",
    "jlpt": "N5",
    "frequency": 4,
    "examples": [
      {
        "japanese": "私しばらくここにいてもいい",
        "english": "Can I stay here for a while?",
        "note": "ここに = at here",
        "furigana": "<ruby>私<rt>わたし</rt></ruby>しばらくここにいてもいい"
      },
      {
        "japanese": "ここにいるよ",
        "english": "I'm right here.",
        "note": "ここに + いる (be at)",
        "furigana": "ここにいるよ"
      }
    ]
  },
  {
    "id": "そこ",
    "word": "そこ",
    "reading": "そこ",
    "pos": "pronoun",
    "meaning": "there, that place",
    "notes": "Mid-distance demonstrative. Near the listener.",
    "jlpt": "N5",
    "frequency": 1,
    "examples": [
      {
        "japanese": "そんなものできるもんですか",
        "english": "Can such a thing really be done?",
        "note": "そんな = such (that kind of)",
        "furigana": "そんなものできるもんですか"
      }
    ]
  },
  {
    "id": "あそこ",
    "word": "あそこ",
    "reading": "あそこ",
    "pos": "pronoun",
    "meaning": "over there",
    "notes": "Far demonstrative. Distant from both speaker and listener.",
    "jlpt": "N5",
    "frequency": 2,
    "examples": [
      {
        "japanese": "あそこからムーミン谷が全部見えるぞ",
        "english": "From up there, you can see all of Moominvalley.",
        "note": "あそこから = from over there",
        "furigana": "あそこからムーミン<ruby>谷<rt>たに</rt></ruby>が<ruby>全部<rt>ぜんぶ</rt></ruby><ruby>見<rt>み</rt></ruby>えるぞ"
      },
      {
        "japanese": "あそこ",
        "english": "Over there.",
        "note": "Short answer pointing",
        "furigana": "あそこ"
      }
    ]
  },
  {
    "id": "何",
    "word": "何",
    "reading": "なに/なん",
    "pos": "pronoun",
    "meaning": "what",
    "notes": "Read なに before consonants, なん before d/n/です.",
    "jlpt": "N5",
    "frequency": 8,
    "examples": [
      {
        "japanese": "何だろうこれは",
        "english": "I wonder what this is.",
        "note": "何だろう = what could it be",
        "furigana": "<ruby>何<rt>なに</rt></ruby>だろうこれは"
      },
      {
        "japanese": "山に登るのは何が面白いのさ",
        "english": "What's so fun about climbing a mountain?",
        "note": "何が = what (subject)",
        "furigana": "<ruby>山<rt>やま</rt></ruby>に<ruby>登<rt>のぼ</rt></ruby>るのは<ruby>何<rt>なに</rt></ruby>が<ruby>面白<rt>おもしろ</rt></ruby>いのさ"
      },
      {
        "japanese": "何を",
        "english": "What?",
        "note": "Short question",
        "furigana": "<ruby>何<rt>なに</rt></ruby>を"
      }
    ]
  },
  {
    "id": "誰",
    "word": "誰",
    "reading": "だれ",
    "pos": "pronoun",
    "meaning": "who",
    "notes": "Question word for people. 誰か = someone.",
    "jlpt": "N5",
    "frequency": 5,
    "examples": [
      {
        "japanese": "誰かが落としていったんだろう",
        "english": "Someone must have dropped it.",
        "note": "誰か = someone",
        "furigana": "<ruby>誰<rt>だれ</rt></ruby>かが<ruby>落<rt>お</rt></ruby>としていったんだろう"
      },
      {
        "japanese": "君は誰だ",
        "english": "Who are you?",
        "note": "Direct question",
        "furigana": "<ruby>君<rt>きみ</rt></ruby>は<ruby>誰<rt>だれ</rt></ruby>だ"
      },
      {
        "japanese": "誰だここでゆで卵を食べたのは",
        "english": "Who ate a boiled egg here?",
        "note": "Topic fronting for emphasis",
        "furigana": "<ruby>誰<rt>だれ</rt></ruby>だここでゆで<ruby>卵<rt>たまご</rt></ruby>を<ruby>食<rt>た</rt></ruby>べたのは"
      }
    ]
  },
  {
    "id": "どこ",
    "word": "どこ",
    "reading": "どこ",
    "pos": "pronoun",
    "meaning": "where",
    "notes": "Question word for place. どこか = somewhere.",
    "jlpt": "N5",
    "frequency": 3,
    "examples": [
      {
        "japanese": "どこ",
        "english": "Where?",
        "note": "Short question",
        "furigana": "どこ"
      },
      {
        "japanese": "ムーミンおまえは一体どこに隠れていたんだ",
        "english": "Moomin, where on earth have you been hiding?",
        "note": "一体 = on earth (emphasis)",
        "furigana": "ムーミンおまえは<ruby>一体<rt>いったい</rt></ruby>どこに<ruby>隠<rt>かく</rt></ruby>れていたんだ"
      },
      {
        "japanese": "あのどこか隠れるところありませんか",
        "english": "Is there anywhere to hide?",
        "note": "どこか = somewhere",
        "furigana": "あのどこか<ruby>隠<rt>かく</rt></ruby>れるところありませんか"
      }
    ]
  },
  {
    "id": "一番",
    "word": "一番",
    "reading": "いちばん",
    "pos": "adverb/noun",
    "meaning": "first, best, most",
    "notes": "Superlative marker. 一番好き = like the most.",
    "jlpt": "N5",
    "frequency": 2,
    "examples": [
      {
        "japanese": "今年あの山に登るのは僕たちが一番なんだぜ",
        "english": "This year, we're the first ones to climb that mountain.",
        "note": "一番 = first",
        "furigana": "<ruby>今年<rt>ことし</rt></ruby>あの<ruby>山<rt>やま</rt></ruby>に<ruby>登<rt>のぼ</rt></ruby>るのは<ruby>僕<rt>ぼく</rt></ruby>たちが<ruby>一番<rt>いちばん</rt></ruby>なんだぜ"
      },
      {
        "japanese": "やっぱりムーミン谷が一番だからね",
        "english": "After all, Moominvalley is the best.",
        "note": "一番 = the best",
        "furigana": "やっぱりムーミン<ruby>谷<rt>たに</rt></ruby>が<ruby>一番<rt>いちばん</rt></ruby>だからね"
      }
    ]
  },
  {
    "id": "今",
    "word": "今",
    "reading": "いま",
    "pos": "noun/adverb",
    "meaning": "now",
    "notes": "今日 (today), 今週 (this week), 今月 (this month).",
    "jlpt": "N5",
    "frequency": 2,
    "examples": [
      {
        "japanese": "今はいないわね",
        "english": "He's not here now.",
        "note": "今は = as for now",
        "furigana": "<ruby>今<rt>いま</rt></ruby>はいないわね"
      },
      {
        "japanese": "今誰か笑わなかったかい",
        "english": "Didn't someone just laugh?",
        "note": "今 = just now",
        "furigana": "<ruby>今<rt>いま</rt></ruby><ruby>誰<rt>だれ</rt></ruby>か<ruby>笑<rt>わら</rt></ruby>わなかったかい"
      }
    ]
  },
  {
    "id": "もう",
    "word": "もう",
    "reading": "もう",
    "pos": "adverb",
    "meaning": "already, soon, more",
    "notes": "Context-dependent. もう一度 = one more time.",
    "jlpt": "N5",
    "frequency": 4,
    "examples": [
      {
        "japanese": "もう一回だな",
        "english": "One more time.",
        "note": "もう一回 = one more time",
        "furigana": "もう<ruby>一<rt>いち</rt></ruby><ruby>回<rt>かい</rt></ruby>だな"
      },
      {
        "japanese": "もう帰らなくちゃ",
        "english": "I have to go home now.",
        "note": "もう = already/now",
        "furigana": "もう<ruby>帰<rt>かえ</rt></ruby>らなくちゃ"
      },
      {
        "japanese": "もう降りたほうがいい",
        "english": "You should probably come down now.",
        "note": "もう = by now",
        "furigana": "もう<ruby>降<rt>お</rt></ruby>りたほうがいい"
      }
    ]
  },
  {
    "id": "まだ",
    "word": "まだ",
    "reading": "まだ",
    "pos": "adverb",
    "meaning": "still, yet",
    "notes": "まだ〜ない = not yet. まだいる = still here.",
    "jlpt": "N5",
    "frequency": 4,
    "examples": [
      {
        "japanese": "あいつはまだ寝てるよきっと",
        "english": "He's probably still asleep.",
        "note": "まだ = still",
        "furigana": "あいつはまだ<ruby>寝<rt>ね</rt></ruby>てるよきっと"
      },
      {
        "japanese": "まだ帰ってないと思うよ",
        "english": "I don't think she is back yet.",
        "note": "まだ〜ない = not yet",
        "furigana": "まだ<ruby>帰<rt>かえ</rt></ruby>ってないと<ruby>思<rt>おも</rt></ruby>うよ"
      },
      {
        "japanese": "僕はまだ眠いよ",
        "english": "I'm still sleepy.",
        "note": "まだ = still",
        "furigana": "<ruby>僕<rt>ぼく</rt></ruby>はまだ<ruby>眠<rt>ねむ</rt></ruby>いよ"
      }
    ]
  },
  {
    "id": "とても",
    "word": "とても",
    "reading": "とても",
    "pos": "adverb",
    "meaning": "very, much",
    "notes": "Emphasizes degree. Similar to すごく (casual).",
    "jlpt": "N5",
    "frequency": 1,
    "examples": [
      {
        "japanese": "だからパパの書く物語はとても長い長いものになりそうでした",
        "english": "That's why the story Papa writes seems to be quite long.",
        "note": "とても長い = very long",
        "furigana": "だからパパの<ruby>書<rt>か</rt></ruby>く<ruby>物語<rt>ものがたり</rt></ruby>はとても<ruby>長<rt>なが</rt></ruby>い<ruby>長<rt>なが</rt></ruby>いものになりそうでした"
      }
    ]
  },
  {
    "id": "ちょっと",
    "word": "ちょっと",
    "reading": "ちょっと",
    "pos": "adverb",
    "meaning": "a little, somewhat",
    "notes": "Also used as softener: ちょっと待って. Very common.",
    "jlpt": "N5",
    "frequency": 2,
    "examples": [
      {
        "japanese": "ムーミンちょっとこっちにおいで",
        "english": "Moomin, come here for a moment.",
        "note": "ちょっと = a moment",
        "furigana": "ムーミンちょっとこっちにおいで"
      },
      {
        "japanese": "ムーミンはしかし心の中でちょっぴり惜しいなと思いました",
        "english": "However, Moomin felt a little regretful inside.",
        "note": "ちょっぴり = a tiny bit",
        "furigana": "ムーミンはしかし<ruby>心<rt>こころ</rt></ruby>の<ruby>中<rt>なか</rt></ruby>でちょっぴり<ruby>惜<rt>お</rt></ruby>しいなと<ruby>思<rt>おも</rt></ruby>いました"
      }
    ]
  },
  {
    "id": "ずっと",
    "word": "ずっと",
    "reading": "ずっと",
    "pos": "adverb",
    "meaning": "all the time, much (more)",
    "notes": "Emphasizes duration or degree of comparison.",
    "jlpt": "N4",
    "frequency": 1,
    "examples": [
      {
        "japanese": "ミムラが帰ってくるまでミーはずっとこの家にいていいんだよ",
        "english": "Until Mimura comes back, you can stay in this house forever.",
        "note": "ずっと = the whole time",
        "furigana": "ミムラが<ruby>帰<rt>かえ</rt></ruby>ってくるまでミーはずっとこの<ruby>家<rt>いえ</rt></ruby>にいていいんだよ"
      }
    ]
  },
  {
    "id": "あ",
    "word": "ああ",
    "reading": "ああ",
    "pos": "interjection",
    "meaning": "ah, oh",
    "notes": "General interjection of realization or agreement.",
    "jlpt": "N5",
    "frequency": 6,
    "examples": [
      {
        "japanese": "ああ楽しかった",
        "english": "Ah, that was fun.",
        "note": "Expression of satisfaction",
        "furigana": "ああ<ruby>楽<rt>たの</rt></ruby>しかった"
      },
      {
        "japanese": "ああ待て",
        "english": "Ah, wait!",
        "note": "Interjection before command",
        "furigana": "ああ<ruby>待<rt>ま</rt></ruby>て"
      }
    ]
  },
  {
    "id": "さあ",
    "word": "さあ",
    "reading": "さあ",
    "pos": "interjection",
    "meaning": "well, now then, come on",
    "notes": "Used to prompt action or express uncertainty.",
    "jlpt": "N4",
    "frequency": 5,
    "examples": [
      {
        "japanese": "さあ降りなさいムーミン",
        "english": "Now, come down, Moomin.",
        "note": "Prompting action",
        "furigana": "さあ<ruby>降<rt>ふ</rt></ruby>りなさいムーミン"
      },
      {
        "japanese": "さあこっちにおいで",
        "english": "Now come over here.",
        "note": "Encouragement",
        "furigana": "さあこっちにおいで"
      },
      {
        "japanese": "さあスニフを起こして何か面白いことをしようよ",
        "english": "Now let's wake up Sniff and do something fun.",
        "note": "Starting proposal",
        "furigana": "さあスニフを<ruby>起<rt>お</rt></ruby>こして<ruby>何<rt>なに</rt></ruby>か<ruby>面白<rt>おもしろ</rt></ruby>いことをしようよ"
      }
    ]
  },
  {
    "id": "やあ",
    "word": "やあ",
    "reading": "やあ",
    "pos": "interjection",
    "meaning": "hey, hi",
    "notes": "Casual greeting. Masculine.",
    "jlpt": "N4",
    "frequency": 2,
    "examples": [
      {
        "japanese": "やあミー君も起きてたのか",
        "english": "Oh, Little My, you're awake too.",
        "note": "Casual greeting",
        "furigana": "やあミー<ruby>君<rt>きみ</rt></ruby>も<ruby>起<rt>お</rt></ruby>きてたのか"
      },
      {
        "japanese": "やあ",
        "english": "Hey.",
        "note": "Simple greeting",
        "furigana": "やあ"
      }
    ]
  },
  {
    "id": "すごい",
    "word": "すごい",
    "reading": "すごい",
    "pos": "i-adjective",
    "meaning": "amazing, great",
    "notes": "Very common in casual speech. すごく as adverb.",
    "jlpt": "N5",
    "frequency": 1,
    "examples": [
      {
        "japanese": "わあ素敵",
        "english": "Wow, amazing!",
        "note": "Exclamation of wonder",
        "furigana": "わあ<ruby>素敵<rt>すてき</rt></ruby>"
      }
    ]
  },
  {
    "id": "危ない",
    "word": "危ない",
    "reading": "あぶない",
    "pos": "i-adjective",
    "meaning": "dangerous",
    "notes": "Used as warning: 危ない！= Watch out!",
    "jlpt": "N4",
    "frequency": 2,
    "examples": [
      {
        "japanese": "危ない触るな爆発したらどうするんだ",
        "english": "It's dangerous, don't touch it! What if it explodes?",
        "note": "Warning",
        "furigana": "<ruby>危<rt>あぶ</rt></ruby>ない<ruby>触<rt>さわ</rt></ruby>るな<ruby>爆発<rt>ばくはつ</rt></ruby>したらどうするんだ"
      },
      {
        "japanese": "早く乗らないと危ないパパ",
        "english": "You have to get on quick, it's dangerous, Dad!",
        "note": "危ない as predicate",
        "furigana": "<ruby>早<rt>はや</rt></ruby>く<ruby>乗<rt>の</rt></ruby>らないと<ruby>危<rt>あぶ</rt></ruby>ないパパ"
      }
    ]
  },
  {
    "id": "かくれんぼ",
    "word": "かくれんぼ",
    "reading": "かくれんぼ",
    "pos": "noun",
    "meaning": "hide and seek",
    "notes": "Children's game. かくれんぼをする = play hide and seek.",
    "jlpt": "N3",
    "frequency": 2,
    "examples": [
      {
        "japanese": "かくれんぼよ",
        "english": "It's hide and seek.",
        "note": "Explaining the game",
        "furigana": "かくれんぼよ"
      },
      {
        "japanese": "ムーミンはかくれんぼの天才ね",
        "english": "Moomin is a hide-and-seek genius, isn't he?",
        "note": "〜の天才 = genius at",
        "furigana": "ムーミンはかくれんぼの<ruby>天才<rt>てんさい</rt></ruby>ね"
      }
    ]
  }
]
